[
  {
    "aptNm": "대경아르체아파트",
    "dealAmount": "28,500",
    "date": "2026-06-01",
    "floor": 5,
    "area": 25.28
  },
  {
    "aptNm": "대경아르체아파트",
    "dealAmount": "37,900",
    "date": "2026-05-22",
    "floor": 15,
    "area": 29.99
  },
  {
    "aptNm": "대경아르체아파트",
    "dealAmount": "37,000",
    "date": "2026-05-10",
    "floor": 7,
    "area": 29.99
  },
  {
    "aptNm": "대경아르체아파트",
    "dealAmount": "35,000",
    "date": "2026-05-07",
    "floor": 6,
    "area": 29.99
  },
  {
    "aptNm": "대경아르체아파트",
    "dealAmount": "35,000",
    "date": "2026-03-02",
    "floor": 6,
    "area": 29.99
  }
]