[
  {
    "aptNm": "신림2차현대",
    "dealAmount": "67,500",
    "date": "2026-07-04",
    "floor": 14,
    "area": 59.91
  },
  {
    "aptNm": "신림2차현대",
    "dealAmount": "80,000",
    "date": "2026-05-23",
    "floor": 14,
    "area": 84.6
  },
  {
    "aptNm": "신림2차현대",
    "dealAmount": "74,000",
    "date": "2026-04-28",
    "floor": 8,
    "area": 84.6
  },
  {
    "aptNm": "신림2차현대",
    "dealAmount": "65,500",
    "date": "2026-04-25",
    "floor": 8,
    "area": 59.91
  },
  {
    "aptNm": "이던필하우스",
    "dealAmount": "13,800",
    "date": "2026-04-16",
    "floor": 7,
    "area": 84.9913
  },
  {
    "aptNm": "이던필하우스",
    "dealAmount": "18,000",
    "date": "2026-02-06",
    "floor": 18,
    "area": 84.9913
  }
]