[
  {
    "aptNm": "문성레이크자이",
    "dealAmount": "41,500",
    "date": "2026-06-27",
    "floor": 21,
    "area": 74.946
  },
  {
    "aptNm": "문성레이크자이",
    "dealAmount": "45,300",
    "date": "2026-06-25",
    "floor": 14,
    "area": 74.9925
  },
  {
    "aptNm": "문성레이크자이",
    "dealAmount": "68,500",
    "date": "2026-06-13",
    "floor": 2,
    "area": 114.9736
  },
  {
    "aptNm": "문성레이크자이",
    "dealAmount": "52,000",
    "date": "2026-06-11",
    "floor": 22,
    "area": 84.92
  },
  {
    "aptNm": "문성레이크자이",
    "dealAmount": "58,500",
    "date": "2026-06-11",
    "floor": 24,
    "area": 101.5079
  },
  {
    "aptNm": "문성레이크자이",
    "dealAmount": "44,700",
    "date": "2026-06-07",
    "floor": 29,
    "area": 74.9925
  },
  {
    "aptNm": "문성레이크자이",
    "dealAmount": "43,600",
    "date": "2026-05-31",
    "floor": 7,
    "area": 74.9925
  },
  {
    "aptNm": "문성레이크자이",
    "dealAmount": "41,900",
    "date": "2026-05-31",
    "floor": 26,
    "area": 74.9925
  },
  {
    "aptNm": "문성레이크자이",
    "dealAmount": "45,000",
    "date": "2026-05-24",
    "floor": 28,
    "area": 74.9925
  },
  {
    "aptNm": "문성레이크자이",
    "dealAmount": "39,000",
    "date": "2026-05-16",
    "floor": 7,
    "area": 74.946
  },
  {
    "aptNm": "문성레이크자이",
    "dealAmount": "46,200",
    "date": "2026-05-16",
    "floor": 12,
    "area": 84.9897
  },
  {
    "aptNm": "문성레이크자이",
    "dealAmount": "55,300",
    "date": "2026-05-13",
    "floor": 5,
    "area": 101.5079
  },
  {
    "aptNm": "문성레이크자이",
    "dealAmount": "43,800",
    "date": "2026-05-12",
    "floor": 27,
    "area": 74.9925
  },
  {
    "aptNm": "문성레이크자이",
    "dealAmount": "43,600",
    "date": "2026-05-05",
    "floor": 18,
    "area": 74.946
  },
  {
    "aptNm": "문성레이크자이",
    "dealAmount": "38,800",
    "date": "2026-05-01",
    "floor": 8,
    "area": 74.946
  },
  {
    "aptNm": "문성레이크자이",
    "dealAmount": "37,800",
    "date": "2026-04-11",
    "floor": 6,
    "area": 74.946
  },
  {
    "aptNm": "문성레이크자이",
    "dealAmount": "52,500",
    "date": "2026-04-09",
    "floor": 17,
    "area": 84.92
  },
  {
    "aptNm": "문성레이크자이",
    "dealAmount": "41,000",
    "date": "2026-03-26",
    "floor": 23,
    "area": 74.946
  },
  {
    "aptNm": "문성레이크자이",
    "dealAmount": "57,500",
    "date": "2026-03-23",
    "floor": 22,
    "area": 101.5079
  },
  {
    "aptNm": "문성레이크자이",
    "dealAmount": "39,000",
    "date": "2026-03-13",
    "floor": 1,
    "area": 74.9925
  },
  {
    "aptNm": "문성레이크자이",
    "dealAmount": "42,500",
    "date": "2026-02-27",
    "floor": 2,
    "area": 84.92
  },
  {
    "aptNm": "문성레이크자이",
    "dealAmount": "43,700",
    "date": "2026-02-10",
    "floor": 23,
    "area": 74.9925
  },
  {
    "aptNm": "문성레이크자이",
    "dealAmount": "43,000",
    "date": "2026-02-07",
    "floor": 15,
    "area": 74.9925
  }
]