[
  {
    "aptNm": "부평삼산엠코타운",
    "dealAmount": "50,000",
    "date": "2026-07-04",
    "floor": 15,
    "area": 84.908
  },
  {
    "aptNm": "부평삼산엠코타운",
    "dealAmount": "51,700",
    "date": "2026-06-23",
    "floor": 18,
    "area": 84.908
  },
  {
    "aptNm": "봉명청솔(3차)",
    "dealAmount": "12,800",
    "date": "2026-06-23",
    "floor": 13,
    "area": 56.34
  },
  {
    "aptNm": "판교원마을12단지(힐스테이트)",
    "dealAmount": "168,000",
    "date": "2026-06-20",
    "floor": 5,
    "area": 101.98
  },
  {
    "aptNm": "용마금호타운",
    "dealAmount": "72,000",
    "date": "2026-06-20",
    "floor": 2,
    "area": 84.9
  },
  {
    "aptNm": "봉명청솔(3차)",
    "dealAmount": "10,000",
    "date": "2026-06-18",
    "floor": 14,
    "area": 56.34
  },
  {
    "aptNm": "봉명청솔(3차)",
    "dealAmount": "10,000",
    "date": "2026-06-18",
    "floor": 1,
    "area": 56.34
  },
  {
    "aptNm": "중앙하이츠빌1단지",
    "dealAmount": "68,000",
    "date": "2026-06-17",
    "floor": 6,
    "area": 59.98
  },
  {
    "aptNm": "중앙하이츠빌1단지",
    "dealAmount": "79,000",
    "date": "2026-06-09",
    "floor": 17,
    "area": 84.98
  },
  {
    "aptNm": "삼익세라믹",
    "dealAmount": "29,500",
    "date": "2026-06-09",
    "floor": 5,
    "area": 46.12
  },
  {
    "aptNm": "래미안트윈파크",
    "dealAmount": "213,500",
    "date": "2026-06-06",
    "floor": 14,
    "area": 84.76
  },
  {
    "aptNm": "판교원마을12단지(힐스테이트)",
    "dealAmount": "220,000",
    "date": "2026-06-03",
    "floor": 15,
    "area": 150.89
  },
  {
    "aptNm": "판교원마을12단지(힐스테이트)",
    "dealAmount": "172,000",
    "date": "2026-06-03",
    "floor": 4,
    "area": 118.6
  },
  {
    "aptNm": "판교원마을12단지(힐스테이트)",
    "dealAmount": "160,000",
    "date": "2026-06-03",
    "floor": 3,
    "area": 101.76
  },
  {
    "aptNm": "중앙하이츠빌1단지",
    "dealAmount": "77,500",
    "date": "2026-06-03",
    "floor": 6,
    "area": 84.98
  },
  {
    "aptNm": "성일",
    "dealAmount": "21,300",
    "date": "2026-06-03",
    "floor": 12,
    "area": 50.88
  },
  {
    "aptNm": "용마금호타운",
    "dealAmount": "71,800",
    "date": "2026-06-02",
    "floor": 12,
    "area": 84.9
  },
  {
    "aptNm": "신흥빌라",
    "dealAmount": "10,000",
    "date": "2026-06-01",
    "floor": 5,
    "area": 84.99
  },
  {
    "aptNm": "판교원마을12단지(힐스테이트)",
    "dealAmount": "171,500",
    "date": "2026-05-29",
    "floor": 6,
    "area": 115.87
  },
  {
    "aptNm": "판교원마을12단지(힐스테이트)",
    "dealAmount": "152,000",
    "date": "2026-05-28",
    "floor": 13,
    "area": 101.98
  },
  {
    "aptNm": "봉명청솔(3차)",
    "dealAmount": "12,400",
    "date": "2026-05-23",
    "floor": 14,
    "area": 56.34
  },
  {
    "aptNm": "판교원마을12단지(힐스테이트)",
    "dealAmount": "172,000",
    "date": "2026-05-21",
    "floor": 8,
    "area": 115.87
  },
  {
    "aptNm": "봉명청솔(3차)",
    "dealAmount": "11,400",
    "date": "2026-05-21",
    "floor": 2,
    "area": 56.34
  },
  {
    "aptNm": "중앙하이츠빌1단지",
    "dealAmount": "70,000",
    "date": "2026-05-20",
    "floor": 1,
    "area": 84.98
  },
  {
    "aptNm": "부평삼산엠코타운",
    "dealAmount": "51,000",
    "date": "2026-05-20",
    "floor": 19,
    "area": 84.908
  },
  {
    "aptNm": "중앙하이츠빌1단지",
    "dealAmount": "63,000",
    "date": "2026-05-19",
    "floor": 6,
    "area": 59.98
  },
  {
    "aptNm": "부평삼산엠코타운",
    "dealAmount": "51,500",
    "date": "2026-05-17",
    "floor": 10,
    "area": 84.908
  },
  {
    "aptNm": "용마금호타운",
    "dealAmount": "66,000",
    "date": "2026-05-16",
    "floor": 2,
    "area": 84.9
  },
  {
    "aptNm": "부평삼산엠코타운",
    "dealAmount": "57,500",
    "date": "2026-05-16",
    "floor": 7,
    "area": 122.059
  },
  {
    "aptNm": "봉명청솔(3차)",
    "dealAmount": "11,750",
    "date": "2026-05-15",
    "floor": 2,
    "area": 56.34
  },
  {
    "aptNm": "봉명청솔(3차)",
    "dealAmount": "13,000",
    "date": "2026-05-14",
    "floor": 11,
    "area": 56.34
  },
  {
    "aptNm": "봉명청솔(3차)",
    "dealAmount": "13,000",
    "date": "2026-05-14",
    "floor": 15,
    "area": 56.34
  },
  {
    "aptNm": "중앙하이츠빌1단지",
    "dealAmount": "77,000",
    "date": "2026-05-12",
    "floor": 10,
    "area": 84.98
  },
  {
    "aptNm": "용마금호타운",
    "dealAmount": "69,500",
    "date": "2026-05-12",
    "floor": 13,
    "area": 84.9
  },
  {
    "aptNm": "부평삼산엠코타운",
    "dealAmount": "57,000",
    "date": "2026-05-09",
    "floor": 12,
    "area": 122.059
  },
  {
    "aptNm": "용마금호타운",
    "dealAmount": "68,000",
    "date": "2026-05-08",
    "floor": 2,
    "area": 84.9
  },
  {
    "aptNm": "봉명청솔(3차)",
    "dealAmount": "11,200",
    "date": "2026-05-08",
    "floor": 4,
    "area": 56.34
  },
  {
    "aptNm": "봉명청솔(3차)",
    "dealAmount": "12,400",
    "date": "2026-05-05",
    "floor": 10,
    "area": 56.34
  },
  {
    "aptNm": "봉명청솔(3차)",
    "dealAmount": "12,000",
    "date": "2026-05-04",
    "floor": 4,
    "area": 56.34
  },
  {
    "aptNm": "판교원마을12단지(힐스테이트)",
    "dealAmount": "167,000",
    "date": "2026-05-01",
    "floor": 7,
    "area": 101.33
  },
  {
    "aptNm": "성일",
    "dealAmount": "22,300",
    "date": "2026-05-01",
    "floor": 13,
    "area": 50.88
  },
  {
    "aptNm": "래미안트윈파크",
    "dealAmount": "207,000",
    "date": "2026-04-29",
    "floor": 27,
    "area": 59.72
  },
  {
    "aptNm": "용마금호타운",
    "dealAmount": "71,500",
    "date": "2026-04-29",
    "floor": 11,
    "area": 84.9
  },
  {
    "aptNm": "부평삼산엠코타운",
    "dealAmount": "39,500",
    "date": "2026-04-29",
    "floor": 16,
    "area": 59.999
  },
  {
    "aptNm": "봉명청솔(3차)",
    "dealAmount": "12,000",
    "date": "2026-04-29",
    "floor": 5,
    "area": 56.34
  },
  {
    "aptNm": "판교원마을12단지(힐스테이트)",
    "dealAmount": "173,000",
    "date": "2026-04-28",
    "floor": 13,
    "area": 118.6
  },
  {
    "aptNm": "중앙하이츠빌1단지",
    "dealAmount": "68,000",
    "date": "2026-04-28",
    "floor": 10,
    "area": 84.98
  },
  {
    "aptNm": "래미안트윈파크",
    "dealAmount": "230,000",
    "date": "2026-04-26",
    "floor": 8,
    "area": 84.76
  },
  {
    "aptNm": "중앙하이츠빌1단지",
    "dealAmount": "74,500",
    "date": "2026-04-26",
    "floor": 2,
    "area": 84.98
  },
  {
    "aptNm": "중앙하이츠빌1단지",
    "dealAmount": "63,000",
    "date": "2026-04-25",
    "floor": 19,
    "area": 59.98
  },
  {
    "aptNm": "용마금호타운",
    "dealAmount": "72,300",
    "date": "2026-04-23",
    "floor": 10,
    "area": 84.9
  },
  {
    "aptNm": "봉명청솔(3차)",
    "dealAmount": "11,100",
    "date": "2026-04-23",
    "floor": 3,
    "area": 56.34
  },
  {
    "aptNm": "용마금호타운",
    "dealAmount": "51,000",
    "date": "2026-04-21",
    "floor": 9,
    "area": 84.9
  },
  {
    "aptNm": "봉명청솔(3차)",
    "dealAmount": "11,600",
    "date": "2026-04-21",
    "floor": 1,
    "area": 56.34
  },
  {
    "aptNm": "용마금호타운",
    "dealAmount": "62,000",
    "date": "2026-04-20",
    "floor": 1,
    "area": 84.9
  },
  {
    "aptNm": "성일",
    "dealAmount": "22,000",
    "date": "2026-04-20",
    "floor": 3,
    "area": 50.88
  },
  {
    "aptNm": "성일",
    "dealAmount": "27,000",
    "date": "2026-04-18",
    "floor": 6,
    "area": 58.98
  },
  {
    "aptNm": "부평삼산엠코타운",
    "dealAmount": "39,500",
    "date": "2026-04-18",
    "floor": 17,
    "area": 59.999
  },
  {
    "aptNm": "래미안트윈파크",
    "dealAmount": "245,000",
    "date": "2026-04-17",
    "floor": 24,
    "area": 84.76
  },
  {
    "aptNm": "성일",
    "dealAmount": "21,500",
    "date": "2026-04-17",
    "floor": 11,
    "area": 50.88
  },
  {
    "aptNm": "중앙하이츠빌1단지",
    "dealAmount": "65,000",
    "date": "2026-04-16",
    "floor": 14,
    "area": 59.98
  },
  {
    "aptNm": "봉명청솔(3차)",
    "dealAmount": "10,800",
    "date": "2026-04-15",
    "floor": 15,
    "area": 56.34
  },
  {
    "aptNm": "봉명청솔(3차)",
    "dealAmount": "12,000",
    "date": "2026-04-15",
    "floor": 8,
    "area": 56.34
  },
  {
    "aptNm": "성일",
    "dealAmount": "21,500",
    "date": "2026-04-12",
    "floor": 3,
    "area": 50.88
  },
  {
    "aptNm": "성일",
    "dealAmount": "21,000",
    "date": "2026-04-11",
    "floor": 5,
    "area": 50.88
  },
  {
    "aptNm": "중앙하이츠빌1단지",
    "dealAmount": "73,500",
    "date": "2026-04-10",
    "floor": 9,
    "area": 84.98
  },
  {
    "aptNm": "용마금호타운",
    "dealAmount": "73,800",
    "date": "2026-04-10",
    "floor": 4,
    "area": 84.9
  },
  {
    "aptNm": "봉명청솔(3차)",
    "dealAmount": "11,100",
    "date": "2026-04-07",
    "floor": 2,
    "area": 56.34
  },
  {
    "aptNm": "봉명청솔(3차)",
    "dealAmount": "13,000",
    "date": "2026-04-04",
    "floor": 4,
    "area": 56.34
  },
  {
    "aptNm": "용마금호타운",
    "dealAmount": "60,000",
    "date": "2026-04-03",
    "floor": 9,
    "area": 84.9
  },
  {
    "aptNm": "봉명청솔(3차)",
    "dealAmount": "12,700",
    "date": "2026-03-31",
    "floor": 14,
    "area": 56.34
  },
  {
    "aptNm": "판교원마을12단지(힐스테이트)",
    "dealAmount": "166,000",
    "date": "2026-03-30",
    "floor": 2,
    "area": 115.87
  },
  {
    "aptNm": "봉명청솔(3차)",
    "dealAmount": "12,700",
    "date": "2026-03-30",
    "floor": 10,
    "area": 56.34
  },
  {
    "aptNm": "용마금호타운",
    "dealAmount": "70,000",
    "date": "2026-03-28",
    "floor": 9,
    "area": 84.9
  },
  {
    "aptNm": "부평삼산엠코타운",
    "dealAmount": "39,500",
    "date": "2026-03-28",
    "floor": 1,
    "area": 59.999
  },
  {
    "aptNm": "봉명청솔(3차)",
    "dealAmount": "12,500",
    "date": "2026-03-28",
    "floor": 13,
    "area": 56.34
  },
  {
    "aptNm": "성일",
    "dealAmount": "26,500",
    "date": "2026-03-27",
    "floor": 11,
    "area": 58.98
  },
  {
    "aptNm": "성일",
    "dealAmount": "22,000",
    "date": "2026-03-25",
    "floor": 2,
    "area": 50.88
  },
  {
    "aptNm": "봉명청솔(3차)",
    "dealAmount": "13,500",
    "date": "2026-03-24",
    "floor": 14,
    "area": 56.34
  },
  {
    "aptNm": "봉명청솔(3차)",
    "dealAmount": "11,800",
    "date": "2026-03-21",
    "floor": 15,
    "area": 56.34
  },
  {
    "aptNm": "봉명청솔(3차)",
    "dealAmount": "12,000",
    "date": "2026-03-21",
    "floor": 14,
    "area": 56.34
  },
  {
    "aptNm": "봉명청솔(3차)",
    "dealAmount": "12,500",
    "date": "2026-03-20",
    "floor": 10,
    "area": 56.34
  },
  {
    "aptNm": "용마금호타운",
    "dealAmount": "71,800",
    "date": "2026-03-17",
    "floor": 13,
    "area": 84.9
  },
  {
    "aptNm": "부평삼산엠코타운",
    "dealAmount": "50,500",
    "date": "2026-03-16",
    "floor": 12,
    "area": 84.908
  },
  {
    "aptNm": "봉명청솔(3차)",
    "dealAmount": "12,200",
    "date": "2026-03-16",
    "floor": 4,
    "area": 56.34
  },
  {
    "aptNm": "봉명청솔(3차)",
    "dealAmount": "12,200",
    "date": "2026-03-12",
    "floor": 2,
    "area": 56.34
  },
  {
    "aptNm": "용마금호타운",
    "dealAmount": "74,000",
    "date": "2026-03-11",
    "floor": 7,
    "area": 84.9
  },
  {
    "aptNm": "봉명청솔(3차)",
    "dealAmount": "9,500",
    "date": "2026-03-11",
    "floor": 3,
    "area": 56.34
  },
  {
    "aptNm": "봉명청솔(3차)",
    "dealAmount": "12,000",
    "date": "2026-03-10",
    "floor": 10,
    "area": 56.34
  },
  {
    "aptNm": "중앙하이츠빌1단지",
    "dealAmount": "59,000",
    "date": "2026-03-08",
    "floor": 3,
    "area": 59.98
  },
  {
    "aptNm": "신흥빌라",
    "dealAmount": "8,600",
    "date": "2026-03-05",
    "floor": 5,
    "area": 84.99
  },
  {
    "aptNm": "용마금호타운",
    "dealAmount": "71,000",
    "date": "2026-03-04",
    "floor": 5,
    "area": 84.9
  },
  {
    "aptNm": "봉명청솔(3차)",
    "dealAmount": "11,400",
    "date": "2026-03-04",
    "floor": 1,
    "area": 56.34
  },
  {
    "aptNm": "봉명청솔(3차)",
    "dealAmount": "11,600",
    "date": "2026-03-03",
    "floor": 15,
    "area": 56.34
  },
  {
    "aptNm": "봉명청솔(3차)",
    "dealAmount": "13,000",
    "date": "2026-02-28",
    "floor": 9,
    "area": 56.34
  },
  {
    "aptNm": "용마금호타운",
    "dealAmount": "50,000",
    "date": "2026-02-27",
    "floor": 10,
    "area": 84.9
  },
  {
    "aptNm": "봉명청솔(3차)",
    "dealAmount": "11,700",
    "date": "2026-02-27",
    "floor": 3,
    "area": 56.34
  },
  {
    "aptNm": "성일",
    "dealAmount": "19,800",
    "date": "2026-02-26",
    "floor": 3,
    "area": 50.88
  },
  {
    "aptNm": "중앙하이츠빌1단지",
    "dealAmount": "68,500",
    "date": "2026-02-23",
    "floor": 5,
    "area": 84.98
  },
  {
    "aptNm": "봉명청솔(3차)",
    "dealAmount": "12,000",
    "date": "2026-02-23",
    "floor": 4,
    "area": 56.34
  },
  {
    "aptNm": "봉명청솔(3차)",
    "dealAmount": "12,700",
    "date": "2026-02-23",
    "floor": 12,
    "area": 56.34
  },
  {
    "aptNm": "중앙하이츠빌1단지",
    "dealAmount": "55,800",
    "date": "2026-02-22",
    "floor": 2,
    "area": 59.98
  },
  {
    "aptNm": "중앙하이츠빌1단지",
    "dealAmount": "63,500",
    "date": "2026-02-21",
    "floor": 4,
    "area": 59.98
  },
  {
    "aptNm": "용마금호타운",
    "dealAmount": "68,200",
    "date": "2026-02-20",
    "floor": 11,
    "area": 84.9
  },
  {
    "aptNm": "신청구상가",
    "dealAmount": "14,000",
    "date": "2026-02-19",
    "floor": 6,
    "area": 84.49
  },
  {
    "aptNm": "봉명청솔(3차)",
    "dealAmount": "11,000",
    "date": "2026-02-19",
    "floor": 1,
    "area": 56.34
  },
  {
    "aptNm": "중앙하이츠빌1단지",
    "dealAmount": "74,800",
    "date": "2026-02-13",
    "floor": 13,
    "area": 84.98
  },
  {
    "aptNm": "봉명청솔(3차)",
    "dealAmount": "12,900",
    "date": "2026-02-13",
    "floor": 4,
    "area": 56.34
  },
  {
    "aptNm": "봉명청솔(3차)",
    "dealAmount": "12,800",
    "date": "2026-02-07",
    "floor": 4,
    "area": 56.34
  },
  {
    "aptNm": "봉명청솔(3차)",
    "dealAmount": "12,300",
    "date": "2026-02-07",
    "floor": 3,
    "area": 56.34
  },
  {
    "aptNm": "봉명청솔(3차)",
    "dealAmount": "11,900",
    "date": "2026-02-04",
    "floor": 12,
    "area": 56.34
  },
  {
    "aptNm": "봉명청솔(3차)",
    "dealAmount": "12,000",
    "date": "2026-02-03",
    "floor": 8,
    "area": 56.34
  }
]