[
  {
    "aptNm": "토성동경동리인타워",
    "dealAmount": "57,000",
    "date": "2026-06-17",
    "floor": 40,
    "area": 79.5266
  },
  {
    "aptNm": "토성동경동리인타워",
    "dealAmount": "39,500",
    "date": "2026-06-02",
    "floor": 7,
    "area": 63.7565
  },
  {
    "aptNm": "자유2",
    "dealAmount": "16,700",
    "date": "2026-06-01",
    "floor": 13,
    "area": 61.38
  },
  {
    "aptNm": "토성동경동리인타워",
    "dealAmount": "53,000",
    "date": "2026-05-28",
    "floor": 42,
    "area": 82.1033
  },
  {
    "aptNm": "토성동경동리인타워",
    "dealAmount": "40,000",
    "date": "2026-05-08",
    "floor": 18,
    "area": 63.7565
  },
  {
    "aptNm": "토성동경동리인타워",
    "dealAmount": "51,000",
    "date": "2026-04-21",
    "floor": 21,
    "area": 82.1611
  },
  {
    "aptNm": "토성동경동리인타워",
    "dealAmount": "58,000",
    "date": "2026-04-14",
    "floor": 35,
    "area": 82.1611
  },
  {
    "aptNm": "토성동경동리인타워",
    "dealAmount": "57,000",
    "date": "2026-04-10",
    "floor": 43,
    "area": 79.5266
  },
  {
    "aptNm": "영산무지개타운",
    "dealAmount": "20,950",
    "date": "2026-04-08",
    "floor": 9,
    "area": 84.975
  },
  {
    "aptNm": "토성동경동리인타워",
    "dealAmount": "44,000",
    "date": "2026-04-06",
    "floor": 4,
    "area": 82.1612
  },
  {
    "aptNm": "토성동경동리인타워",
    "dealAmount": "47,500",
    "date": "2026-03-26",
    "floor": 38,
    "area": 77.0845
  },
  {
    "aptNm": "토성동경동리인타워",
    "dealAmount": "42,500",
    "date": "2026-03-26",
    "floor": 32,
    "area": 63.7565
  },
  {
    "aptNm": "토성동경동리인타워",
    "dealAmount": "50,000",
    "date": "2026-03-20",
    "floor": 35,
    "area": 82.1033
  },
  {
    "aptNm": "토성동경동리인타워",
    "dealAmount": "49,000",
    "date": "2026-03-12",
    "floor": 42,
    "area": 77.0845
  },
  {
    "aptNm": "하이트뷰아파트",
    "dealAmount": "24,500",
    "date": "2026-03-09",
    "floor": 6,
    "area": 56.58
  },
  {
    "aptNm": "영산무지개타운",
    "dealAmount": "16,300",
    "date": "2026-03-07",
    "floor": 8,
    "area": 67.54
  },
  {
    "aptNm": "토성동경동리인타워",
    "dealAmount": "44,300",
    "date": "2026-03-01",
    "floor": 21,
    "area": 77.0845
  },
  {
    "aptNm": "하이트뷰아파트",
    "dealAmount": "24,500",
    "date": "2026-02-27",
    "floor": 8,
    "area": 52.64
  },
  {
    "aptNm": "토성동경동리인타워",
    "dealAmount": "56,500",
    "date": "2026-02-27",
    "floor": 17,
    "area": 82.1612
  },
  {
    "aptNm": "토성동경동리인타워",
    "dealAmount": "54,000",
    "date": "2026-02-27",
    "floor": 18,
    "area": 82.1612
  }
]