[
  {
    "aptNm": "더샵센텀파크2차",
    "dealAmount": "135,000",
    "date": "2026-06-15",
    "floor": 41,
    "area": 127.489
  },
  {
    "aptNm": "더샵센텀파크2차",
    "dealAmount": "113,000",
    "date": "2026-06-15",
    "floor": 19,
    "area": 84.6389
  },
  {
    "aptNm": "더샵센텀파크2차",
    "dealAmount": "128,000",
    "date": "2026-06-13",
    "floor": 9,
    "area": 127.489
  },
  {
    "aptNm": "더샵센텀파크2차",
    "dealAmount": "109,500",
    "date": "2026-06-13",
    "floor": 17,
    "area": 84.6389
  },
  {
    "aptNm": "더샵센텀파크2차",
    "dealAmount": "108,000",
    "date": "2026-05-07",
    "floor": 19,
    "area": 84.6528
  },
  {
    "aptNm": "더샵센텀파크2차",
    "dealAmount": "133,000",
    "date": "2026-04-28",
    "floor": 19,
    "area": 127.489
  },
  {
    "aptNm": "더샵센텀파크2차",
    "dealAmount": "104,000",
    "date": "2026-04-25",
    "floor": 37,
    "area": 84.6389
  },
  {
    "aptNm": "더샵센텀파크2차",
    "dealAmount": "114,500",
    "date": "2026-04-24",
    "floor": 11,
    "area": 100.945
  },
  {
    "aptNm": "그린시아아파트101동",
    "dealAmount": "28,000",
    "date": "2026-04-20",
    "floor": 8,
    "area": 84.16
  },
  {
    "aptNm": "더샵센텀파크2차",
    "dealAmount": "101,000",
    "date": "2026-04-03",
    "floor": 9,
    "area": 84.6389
  },
  {
    "aptNm": "더샵센텀파크2차",
    "dealAmount": "125,000",
    "date": "2026-02-26",
    "floor": 40,
    "area": 100.945
  },
  {
    "aptNm": "더샵센텀파크2차",
    "dealAmount": "109,000",
    "date": "2026-02-19",
    "floor": 36,
    "area": 84.6389
  }
]