[
  {
    "aptNm": "시흥5차푸르지오",
    "dealAmount": "40,000",
    "date": "2026-05-23",
    "floor": 8,
    "area": 59.8272
  },
  {
    "aptNm": "시흥5차푸르지오",
    "dealAmount": "38,500",
    "date": "2026-04-28",
    "floor": 4,
    "area": 93.8949
  },
  {
    "aptNm": "시흥5차푸르지오",
    "dealAmount": "34,057",
    "date": "2026-04-06",
    "floor": 15,
    "area": 111.1902
  },
  {
    "aptNm": "시흥5차푸르지오",
    "dealAmount": "54,700",
    "date": "2026-03-10",
    "floor": 28,
    "area": 122.932
  }
]