[
  {
    "aptNm": "더샵파크리치",
    "dealAmount": "65,000",
    "date": "2026-06-27",
    "floor": 17,
    "area": 84.98
  },
  {
    "aptNm": "더샵파크리치",
    "dealAmount": "59,000",
    "date": "2026-05-23",
    "floor": 4,
    "area": 84.98
  },
  {
    "aptNm": "더샵파크리치",
    "dealAmount": "59,500",
    "date": "2026-04-15",
    "floor": 2,
    "area": 84.98
  },
  {
    "aptNm": "제일맨션",
    "dealAmount": "13,800",
    "date": "2026-04-07",
    "floor": 1,
    "area": 84.74
  },
  {
    "aptNm": "더샵파크리치",
    "dealAmount": "88,000",
    "date": "2026-04-02",
    "floor": 11,
    "area": 179.4912
  },
  {
    "aptNm": "제일맨션",
    "dealAmount": "8,500",
    "date": "2026-03-20",
    "floor": 12,
    "area": 59.65
  },
  {
    "aptNm": "더샵파크리치",
    "dealAmount": "74,500",
    "date": "2026-02-20",
    "floor": 27,
    "area": 117.6106
  },
  {
    "aptNm": "더샵파크리치",
    "dealAmount": "62,000",
    "date": "2026-02-09",
    "floor": 19,
    "area": 84.98
  },
  {
    "aptNm": "더샵파크리치",
    "dealAmount": "71,500",
    "date": "2026-02-04",
    "floor": 7,
    "area": 117.6106
  }
]