[
  {
    "aptNm": "해맞이그린빌1단지",
    "dealAmount": "22,000",
    "date": "2026-06-03",
    "floor": 17,
    "area": 109.95
  },
  {
    "aptNm": "해맞이그린빌1단지",
    "dealAmount": "22,500",
    "date": "2026-06-02",
    "floor": 5,
    "area": 109.95
  },
  {
    "aptNm": "해맞이그린빌1단지",
    "dealAmount": "18,000",
    "date": "2026-06-01",
    "floor": 22,
    "area": 84.76
  },
  {
    "aptNm": "해맞이그린빌1단지",
    "dealAmount": "24,300",
    "date": "2026-05-29",
    "floor": 16,
    "area": 109.95
  },
  {
    "aptNm": "해맞이그린빌1단지",
    "dealAmount": "17,000",
    "date": "2026-05-21",
    "floor": 19,
    "area": 84.76
  },
  {
    "aptNm": "해맞이그린빌1단지",
    "dealAmount": "13,800",
    "date": "2026-05-19",
    "floor": 19,
    "area": 59.94
  },
  {
    "aptNm": "해맞이그린빌1단지",
    "dealAmount": "12,500",
    "date": "2026-05-16",
    "floor": 4,
    "area": 59.9
  },
  {
    "aptNm": "해맞이그린빌1단지",
    "dealAmount": "15,900",
    "date": "2026-05-16",
    "floor": 23,
    "area": 76.74
  },
  {
    "aptNm": "해맞이그린빌1단지",
    "dealAmount": "18,800",
    "date": "2026-05-11",
    "floor": 17,
    "area": 84.76
  },
  {
    "aptNm": "해맞이그린빌1단지",
    "dealAmount": "23,300",
    "date": "2026-05-09",
    "floor": 17,
    "area": 109.95
  },
  {
    "aptNm": "해맞이그린빌1단지",
    "dealAmount": "13,000",
    "date": "2026-05-06",
    "floor": 6,
    "area": 59.94
  },
  {
    "aptNm": "해맞이그린빌1단지",
    "dealAmount": "13,000",
    "date": "2026-04-30",
    "floor": 14,
    "area": 59.9
  },
  {
    "aptNm": "해맞이그린빌1단지",
    "dealAmount": "9,900",
    "date": "2026-04-28",
    "floor": 8,
    "area": 39.94
  },
  {
    "aptNm": "해맞이그린빌1단지",
    "dealAmount": "13,500",
    "date": "2026-04-20",
    "floor": 22,
    "area": 59.94
  },
  {
    "aptNm": "해맞이그린빌1단지",
    "dealAmount": "21,500",
    "date": "2026-04-17",
    "floor": 4,
    "area": 109.95
  },
  {
    "aptNm": "해맞이그린빌1단지",
    "dealAmount": "10,500",
    "date": "2026-04-16",
    "floor": 7,
    "area": 39.94
  },
  {
    "aptNm": "해맞이그린빌1단지",
    "dealAmount": "12,800",
    "date": "2026-04-09",
    "floor": 11,
    "area": 59.94
  },
  {
    "aptNm": "해맞이그린빌1단지",
    "dealAmount": "17,700",
    "date": "2026-04-08",
    "floor": 23,
    "area": 84.76
  },
  {
    "aptNm": "해맞이그린빌1단지",
    "dealAmount": "16,500",
    "date": "2026-04-05",
    "floor": 1,
    "area": 76.74
  },
  {
    "aptNm": "해맞이그린빌1단지",
    "dealAmount": "16,600",
    "date": "2026-04-05",
    "floor": 1,
    "area": 84.76
  },
  {
    "aptNm": "해맞이그린빌1단지",
    "dealAmount": "12,900",
    "date": "2026-03-30",
    "floor": 7,
    "area": 59.94
  },
  {
    "aptNm": "해맞이그린빌1단지",
    "dealAmount": "18,000",
    "date": "2026-03-14",
    "floor": 14,
    "area": 84.76
  },
  {
    "aptNm": "해맞이그린빌1단지",
    "dealAmount": "17,200",
    "date": "2026-03-10",
    "floor": 19,
    "area": 84.76
  },
  {
    "aptNm": "해맞이그린빌1단지",
    "dealAmount": "13,200",
    "date": "2026-03-07",
    "floor": 15,
    "area": 59.9
  },
  {
    "aptNm": "해맞이그린빌1단지",
    "dealAmount": "18,400",
    "date": "2026-03-04",
    "floor": 5,
    "area": 84.76
  },
  {
    "aptNm": "해맞이그린빌1단지",
    "dealAmount": "13,000",
    "date": "2026-02-20",
    "floor": 5,
    "area": 59.94
  },
  {
    "aptNm": "해맞이그린빌1단지",
    "dealAmount": "17,200",
    "date": "2026-02-15",
    "floor": 16,
    "area": 84.76
  },
  {
    "aptNm": "해맞이그린빌1단지",
    "dealAmount": "13,300",
    "date": "2026-02-09",
    "floor": 20,
    "area": 59.94
  },
  {
    "aptNm": "해맞이그린빌1단지",
    "dealAmount": "14,000",
    "date": "2026-02-07",
    "floor": 20,
    "area": 59.9
  },
  {
    "aptNm": "해맞이그린빌1단지",
    "dealAmount": "12,500",
    "date": "2026-02-07",
    "floor": 19,
    "area": 59.9
  },
  {
    "aptNm": "해맞이그린빌1단지",
    "dealAmount": "16,000",
    "date": "2026-02-05",
    "floor": 19,
    "area": 76.74
  },
  {
    "aptNm": "삼성래미안",
    "dealAmount": "10,300",
    "date": "2026-02-04",
    "floor": 7,
    "area": 84.94
  },
  {
    "aptNm": "해맞이그린빌1단지",
    "dealAmount": "23,800",
    "date": "2026-02-03",
    "floor": 5,
    "area": 109.95
  }
]