[
  {
    "aptNm": "대구역 서희스타힐스",
    "dealAmount": "35,300",
    "date": "2026-07-10",
    "floor": 4,
    "area": 84.84
  },
  {
    "aptNm": "대구역 서희스타힐스",
    "dealAmount": "40,500",
    "date": "2026-07-04",
    "floor": 14,
    "area": 84.49
  },
  {
    "aptNm": "늘푸른동아",
    "dealAmount": "88,000",
    "date": "2026-07-01",
    "floor": 2,
    "area": 84.97
  },
  {
    "aptNm": "늘푸른동아",
    "dealAmount": "85,500",
    "date": "2026-06-30",
    "floor": 8,
    "area": 84.97
  },
  {
    "aptNm": "등촌동아이파크",
    "dealAmount": "120,000",
    "date": "2026-06-27",
    "floor": 19,
    "area": 84.7556
  },
  {
    "aptNm": "등촌동아이파크",
    "dealAmount": "150,000",
    "date": "2026-06-27",
    "floor": 7,
    "area": 165.8299
  },
  {
    "aptNm": "늘푸른동아",
    "dealAmount": "74,000",
    "date": "2026-06-26",
    "floor": 15,
    "area": 59.65
  },
  {
    "aptNm": "시영3차(라이프)아파트",
    "dealAmount": "45,000",
    "date": "2026-06-24",
    "floor": 13,
    "area": 39.6
  },
  {
    "aptNm": "대창2",
    "dealAmount": "12,500",
    "date": "2026-06-23",
    "floor": 7,
    "area": 59.55
  },
  {
    "aptNm": "대구역 서희스타힐스",
    "dealAmount": "40,000",
    "date": "2026-06-22",
    "floor": 20,
    "area": 84.49
  },
  {
    "aptNm": "대구역 서희스타힐스",
    "dealAmount": "36,500",
    "date": "2026-06-20",
    "floor": 3,
    "area": 84.84
  },
  {
    "aptNm": "엘에이치피닉스포레",
    "dealAmount": "37,000",
    "date": "2026-06-19",
    "floor": 4,
    "area": 84.92
  },
  {
    "aptNm": "대구역 서희스타힐스",
    "dealAmount": "39,000",
    "date": "2026-06-19",
    "floor": 14,
    "area": 84.84
  },
  {
    "aptNm": "서창베라체아파트(11단지)",
    "dealAmount": "36,000",
    "date": "2026-06-18",
    "floor": 16,
    "area": 59.49
  },
  {
    "aptNm": "서창베라체아파트(11단지)",
    "dealAmount": "35,400",
    "date": "2026-06-17",
    "floor": 12,
    "area": 59.49
  },
  {
    "aptNm": "늘푸른동아",
    "dealAmount": "71,500",
    "date": "2026-06-16",
    "floor": 12,
    "area": 59.65
  },
  {
    "aptNm": "반도보라빌",
    "dealAmount": "15,000",
    "date": "2026-06-15",
    "floor": 2,
    "area": 84.96
  },
  {
    "aptNm": "대구역 서희스타힐스",
    "dealAmount": "30,500",
    "date": "2026-06-15",
    "floor": 9,
    "area": 59.87
  },
  {
    "aptNm": "서창베라체아파트(11단지)",
    "dealAmount": "35,000",
    "date": "2026-06-15",
    "floor": 8,
    "area": 59.85
  },
  {
    "aptNm": "등촌동아이파크",
    "dealAmount": "128,000",
    "date": "2026-06-13",
    "floor": 16,
    "area": 84.9958
  },
  {
    "aptNm": "등촌동아이파크",
    "dealAmount": "143,000",
    "date": "2026-06-11",
    "floor": 14,
    "area": 134.8836
  },
  {
    "aptNm": "엘에이치피닉스포레",
    "dealAmount": "40,500",
    "date": "2026-06-10",
    "floor": 4,
    "area": 84.99
  },
  {
    "aptNm": "시영3차(라이프)아파트",
    "dealAmount": "47,000",
    "date": "2026-06-07",
    "floor": 6,
    "area": 39.6
  },
  {
    "aptNm": "엘에이치피닉스포레",
    "dealAmount": "40,800",
    "date": "2026-06-06",
    "floor": 3,
    "area": 84.92
  },
  {
    "aptNm": "등촌동아이파크",
    "dealAmount": "128,000",
    "date": "2026-06-04",
    "floor": 10,
    "area": 84.9958
  },
  {
    "aptNm": "대구역 서희스타힐스",
    "dealAmount": "27,500",
    "date": "2026-06-03",
    "floor": 2,
    "area": 59.93
  },
  {
    "aptNm": "등촌동아이파크",
    "dealAmount": "136,000",
    "date": "2026-05-30",
    "floor": 1,
    "area": 165.8299
  },
  {
    "aptNm": "등촌동아이파크",
    "dealAmount": "125,300",
    "date": "2026-05-30",
    "floor": 9,
    "area": 84.7556
  },
  {
    "aptNm": "시영3차(라이프)아파트",
    "dealAmount": "30,000",
    "date": "2026-05-30",
    "floor": 10,
    "area": 34.44
  },
  {
    "aptNm": "등촌동아이파크",
    "dealAmount": "138,500",
    "date": "2026-05-28",
    "floor": 8,
    "area": 119.9031
  },
  {
    "aptNm": "시영3차(라이프)아파트",
    "dealAmount": "37,500",
    "date": "2026-05-27",
    "floor": 9,
    "area": 39.6
  },
  {
    "aptNm": "중앙하이츠빌",
    "dealAmount": "200,000",
    "date": "2026-05-26",
    "floor": 6,
    "area": 84.9673
  },
  {
    "aptNm": "엘에이치피닉스포레",
    "dealAmount": "42,300",
    "date": "2026-05-25",
    "floor": 8,
    "area": 84.99
  },
  {
    "aptNm": "등촌동아이파크",
    "dealAmount": "138,800",
    "date": "2026-05-23",
    "floor": 10,
    "area": 134.9883
  },
  {
    "aptNm": "등촌동아이파크",
    "dealAmount": "126,500",
    "date": "2026-05-23",
    "floor": 4,
    "area": 134.8836
  },
  {
    "aptNm": "등촌동아이파크",
    "dealAmount": "141,500",
    "date": "2026-05-22",
    "floor": 8,
    "area": 165.8299
  },
  {
    "aptNm": "반도보라빌",
    "dealAmount": "13,200",
    "date": "2026-05-20",
    "floor": 8,
    "area": 84.96
  },
  {
    "aptNm": "대주피오레",
    "dealAmount": "32,300",
    "date": "2026-05-18",
    "floor": 12,
    "area": 84.9888
  },
  {
    "aptNm": "엘에이치피닉스포레",
    "dealAmount": "42,000",
    "date": "2026-05-15",
    "floor": 14,
    "area": 84.92
  },
  {
    "aptNm": "등촌동아이파크",
    "dealAmount": "139,000",
    "date": "2026-05-15",
    "floor": 10,
    "area": 134.8836
  },
  {
    "aptNm": "시영3차(라이프)아파트",
    "dealAmount": "31,500",
    "date": "2026-05-15",
    "floor": 5,
    "area": 34.44
  },
  {
    "aptNm": "대구역 서희스타힐스",
    "dealAmount": "30,000",
    "date": "2026-05-14",
    "floor": 3,
    "area": 59.87
  },
  {
    "aptNm": "시영3차(라이프)아파트",
    "dealAmount": "38,300",
    "date": "2026-05-14",
    "floor": 7,
    "area": 39.6
  },
  {
    "aptNm": "우빈가온",
    "dealAmount": "7,700",
    "date": "2026-05-14",
    "floor": 4,
    "area": 21.59
  },
  {
    "aptNm": "대구역 서희스타힐스",
    "dealAmount": "40,500",
    "date": "2026-05-13",
    "floor": 11,
    "area": 84.49
  },
  {
    "aptNm": "시영3차(라이프)아파트",
    "dealAmount": "40,900",
    "date": "2026-05-13",
    "floor": 4,
    "area": 39.6
  },
  {
    "aptNm": "시영3차(라이프)아파트",
    "dealAmount": "36,000",
    "date": "2026-05-12",
    "floor": 14,
    "area": 34.44
  },
  {
    "aptNm": "대구역 서희스타힐스",
    "dealAmount": "37,700",
    "date": "2026-05-11",
    "floor": 5,
    "area": 74.68
  },
  {
    "aptNm": "대구역 서희스타힐스",
    "dealAmount": "28,200",
    "date": "2026-05-09",
    "floor": 21,
    "area": 59.93
  },
  {
    "aptNm": "늘푸른동아",
    "dealAmount": "85,000",
    "date": "2026-05-08",
    "floor": 9,
    "area": 84.97
  },
  {
    "aptNm": "서창베라체아파트(11단지)",
    "dealAmount": "35,000",
    "date": "2026-05-08",
    "floor": 13,
    "area": 59.49
  },
  {
    "aptNm": "늘푸른동아",
    "dealAmount": "84,800",
    "date": "2026-05-06",
    "floor": 12,
    "area": 84.97
  },
  {
    "aptNm": "엘에이치피닉스포레",
    "dealAmount": "30,000",
    "date": "2026-05-05",
    "floor": 10,
    "area": 84.99
  },
  {
    "aptNm": "늘푸른동아",
    "dealAmount": "83,000",
    "date": "2026-05-05",
    "floor": 19,
    "area": 84.97
  },
  {
    "aptNm": "등촌동아이파크",
    "dealAmount": "136,500",
    "date": "2026-05-04",
    "floor": 19,
    "area": 134.8836
  },
  {
    "aptNm": "시영3차(라이프)아파트",
    "dealAmount": "34,500",
    "date": "2026-05-04",
    "floor": 1,
    "area": 39.6
  },
  {
    "aptNm": "늘푸른동아",
    "dealAmount": "72,000",
    "date": "2026-05-02",
    "floor": 6,
    "area": 59.65
  },
  {
    "aptNm": "등촌동아이파크",
    "dealAmount": "125,000",
    "date": "2026-05-01",
    "floor": 10,
    "area": 165.8299
  },
  {
    "aptNm": "반도보라빌",
    "dealAmount": "14,700",
    "date": "2026-04-30",
    "floor": 6,
    "area": 84.96
  },
  {
    "aptNm": "대구역 서희스타힐스",
    "dealAmount": "37,000",
    "date": "2026-04-29",
    "floor": 12,
    "area": 84.84
  },
  {
    "aptNm": "대구역 서희스타힐스",
    "dealAmount": "31,000",
    "date": "2026-04-29",
    "floor": 20,
    "area": 59.93
  },
  {
    "aptNm": "등촌동아이파크",
    "dealAmount": "112,000",
    "date": "2026-04-29",
    "floor": 8,
    "area": 84.7556
  },
  {
    "aptNm": "대구역 서희스타힐스",
    "dealAmount": "35,500",
    "date": "2026-04-26",
    "floor": 22,
    "area": 74.68
  },
  {
    "aptNm": "대구역 서희스타힐스",
    "dealAmount": "37,400",
    "date": "2026-04-25",
    "floor": 16,
    "area": 84.49
  },
  {
    "aptNm": "등촌동아이파크",
    "dealAmount": "147,000",
    "date": "2026-04-25",
    "floor": 19,
    "area": 165.8299
  },
  {
    "aptNm": "등촌동아이파크",
    "dealAmount": "124,900",
    "date": "2026-04-25",
    "floor": 11,
    "area": 84.9958
  },
  {
    "aptNm": "중앙하이츠빌",
    "dealAmount": "210,000",
    "date": "2026-04-25",
    "floor": 9,
    "area": 84.9673
  },
  {
    "aptNm": "대구역 서희스타힐스",
    "dealAmount": "34,000",
    "date": "2026-04-24",
    "floor": 10,
    "area": 59.91
  },
  {
    "aptNm": "대구역 서희스타힐스",
    "dealAmount": "30,000",
    "date": "2026-04-24",
    "floor": 8,
    "area": 59.93
  },
  {
    "aptNm": "등촌동아이파크",
    "dealAmount": "131,000",
    "date": "2026-04-24",
    "floor": 8,
    "area": 119.9031
  },
  {
    "aptNm": "시영3차(라이프)아파트",
    "dealAmount": "54,000",
    "date": "2026-04-24",
    "floor": 11,
    "area": 49.5
  },
  {
    "aptNm": "서창베라체아파트(11단지)",
    "dealAmount": "38,250",
    "date": "2026-04-22",
    "floor": 5,
    "area": 84.99
  },
  {
    "aptNm": "늘푸른동아",
    "dealAmount": "85,000",
    "date": "2026-04-21",
    "floor": 8,
    "area": 84.97
  },
  {
    "aptNm": "대주피오레",
    "dealAmount": "36,000",
    "date": "2026-04-20",
    "floor": 1,
    "area": 123.3203
  },
  {
    "aptNm": "엘에이치피닉스포레",
    "dealAmount": "44,000",
    "date": "2026-04-20",
    "floor": 12,
    "area": 84.99
  },
  {
    "aptNm": "시영3차(라이프)아파트",
    "dealAmount": "53,000",
    "date": "2026-04-20",
    "floor": 15,
    "area": 49.5
  },
  {
    "aptNm": "등촌동아이파크",
    "dealAmount": "134,000",
    "date": "2026-04-17",
    "floor": 5,
    "area": 134.9883
  },
  {
    "aptNm": "시영3차(라이프)아파트",
    "dealAmount": "31,900",
    "date": "2026-04-16",
    "floor": 8,
    "area": 34.44
  },
  {
    "aptNm": "등촌동아이파크",
    "dealAmount": "123,000",
    "date": "2026-04-15",
    "floor": 7,
    "area": 84.9958
  },
  {
    "aptNm": "등촌동아이파크",
    "dealAmount": "135,000",
    "date": "2026-04-15",
    "floor": 11,
    "area": 134.8836
  },
  {
    "aptNm": "시영3차(라이프)아파트",
    "dealAmount": "35,500",
    "date": "2026-04-15",
    "floor": 10,
    "area": 39.6
  },
  {
    "aptNm": "등촌동아이파크",
    "dealAmount": "117,000",
    "date": "2026-04-14",
    "floor": 14,
    "area": 84.9958
  },
  {
    "aptNm": "등촌동아이파크",
    "dealAmount": "109,500",
    "date": "2026-04-14",
    "floor": 4,
    "area": 84.7556
  },
  {
    "aptNm": "시영3차(라이프)아파트",
    "dealAmount": "32,000",
    "date": "2026-04-14",
    "floor": 4,
    "area": 34.44
  },
  {
    "aptNm": "대구역 서희스타힐스",
    "dealAmount": "34,700",
    "date": "2026-04-10",
    "floor": 1,
    "area": 84.49
  },
  {
    "aptNm": "시영3차(라이프)아파트",
    "dealAmount": "41,300",
    "date": "2026-04-09",
    "floor": 7,
    "area": 39.6
  },
  {
    "aptNm": "대구역 서희스타힐스",
    "dealAmount": "30,500",
    "date": "2026-04-08",
    "floor": 12,
    "area": 59.85
  },
  {
    "aptNm": "서창베라체아파트(11단지)",
    "dealAmount": "33,000",
    "date": "2026-04-06",
    "floor": 5,
    "area": 59.49
  },
  {
    "aptNm": "서창베라체아파트(11단지)",
    "dealAmount": "32,000",
    "date": "2026-04-06",
    "floor": 3,
    "area": 59.85
  },
  {
    "aptNm": "대주피오레",
    "dealAmount": "35,600",
    "date": "2026-04-04",
    "floor": 9,
    "area": 123.3203
  },
  {
    "aptNm": "대구역 서희스타힐스",
    "dealAmount": "30,500",
    "date": "2026-04-04",
    "floor": 16,
    "area": 59.93
  },
  {
    "aptNm": "시영3차(라이프)아파트",
    "dealAmount": "38,000",
    "date": "2026-04-04",
    "floor": 5,
    "area": 39.6
  },
  {
    "aptNm": "시영3차(라이프)아파트",
    "dealAmount": "38,800",
    "date": "2026-04-04",
    "floor": 9,
    "area": 39.6
  },
  {
    "aptNm": "시영3차(라이프)아파트",
    "dealAmount": "31,000",
    "date": "2026-04-04",
    "floor": 7,
    "area": 34.44
  },
  {
    "aptNm": "엘에이치피닉스포레",
    "dealAmount": "38,000",
    "date": "2026-04-03",
    "floor": 4,
    "area": 84.99
  },
  {
    "aptNm": "대구역 서희스타힐스",
    "dealAmount": "30,000",
    "date": "2026-04-03",
    "floor": 18,
    "area": 59.91
  },
  {
    "aptNm": "대구역 서희스타힐스",
    "dealAmount": "36,500",
    "date": "2026-04-02",
    "floor": 20,
    "area": 74.68
  },
  {
    "aptNm": "반도보라빌",
    "dealAmount": "14,500",
    "date": "2026-04-01",
    "floor": 4,
    "area": 84.96
  },
  {
    "aptNm": "반도보라빌",
    "dealAmount": "14,000",
    "date": "2026-04-01",
    "floor": 1,
    "area": 84.96
  },
  {
    "aptNm": "등촌동아이파크",
    "dealAmount": "123,000",
    "date": "2026-04-01",
    "floor": 12,
    "area": 84.9958
  },
  {
    "aptNm": "엘에이치피닉스포레",
    "dealAmount": "41,500",
    "date": "2026-03-29",
    "floor": 2,
    "area": 84.99
  },
  {
    "aptNm": "시영3차(라이프)아파트",
    "dealAmount": "40,800",
    "date": "2026-03-28",
    "floor": 14,
    "area": 39.6
  },
  {
    "aptNm": "서창베라체아파트(11단지)",
    "dealAmount": "40,300",
    "date": "2026-03-28",
    "floor": 10,
    "area": 84.99
  },
  {
    "aptNm": "시영3차(라이프)아파트",
    "dealAmount": "31,500",
    "date": "2026-03-27",
    "floor": 2,
    "area": 34.44
  },
  {
    "aptNm": "시영3차(라이프)아파트",
    "dealAmount": "32,900",
    "date": "2026-03-27",
    "floor": 9,
    "area": 34.44
  },
  {
    "aptNm": "대구역 서희스타힐스",
    "dealAmount": "35,400",
    "date": "2026-03-26",
    "floor": 1,
    "area": 84.49
  },
  {
    "aptNm": "대구역 서희스타힐스",
    "dealAmount": "38,200",
    "date": "2026-03-26",
    "floor": 13,
    "area": 84.84
  },
  {
    "aptNm": "등촌동아이파크",
    "dealAmount": "138,000",
    "date": "2026-03-24",
    "floor": 18,
    "area": 134.9883
  },
  {
    "aptNm": "시영3차(라이프)아파트",
    "dealAmount": "38,300",
    "date": "2026-03-24",
    "floor": 6,
    "area": 39.6
  },
  {
    "aptNm": "대구역 서희스타힐스",
    "dealAmount": "27,900",
    "date": "2026-03-22",
    "floor": 3,
    "area": 59.91
  },
  {
    "aptNm": "대구역 서희스타힐스",
    "dealAmount": "38,000",
    "date": "2026-03-21",
    "floor": 23,
    "area": 74.68
  },
  {
    "aptNm": "엘에이치피닉스포레",
    "dealAmount": "42,200",
    "date": "2026-03-20",
    "floor": 9,
    "area": 84.99
  },
  {
    "aptNm": "등촌동아이파크",
    "dealAmount": "134,000",
    "date": "2026-03-20",
    "floor": 11,
    "area": 134.9883
  },
  {
    "aptNm": "시영3차(라이프)아파트",
    "dealAmount": "36,000",
    "date": "2026-03-19",
    "floor": 5,
    "area": 39.6
  },
  {
    "aptNm": "대구역 서희스타힐스",
    "dealAmount": "30,000",
    "date": "2026-03-18",
    "floor": 9,
    "area": 59.85
  },
  {
    "aptNm": "시영3차(라이프)아파트",
    "dealAmount": "39,500",
    "date": "2026-03-16",
    "floor": 8,
    "area": 39.6
  },
  {
    "aptNm": "서창베라체아파트(11단지)",
    "dealAmount": "40,000",
    "date": "2026-03-14",
    "floor": 18,
    "area": 84.99
  },
  {
    "aptNm": "시영3차(라이프)아파트",
    "dealAmount": "53,000",
    "date": "2026-03-12",
    "floor": 9,
    "area": 49.5
  },
  {
    "aptNm": "엘에이치피닉스포레",
    "dealAmount": "35,500",
    "date": "2026-03-11",
    "floor": 2,
    "area": 84.92
  },
  {
    "aptNm": "시영3차(라이프)아파트",
    "dealAmount": "38,900",
    "date": "2026-03-11",
    "floor": 13,
    "area": 39.6
  },
  {
    "aptNm": "등촌동아이파크",
    "dealAmount": "116,000",
    "date": "2026-03-10",
    "floor": 6,
    "area": 84.7556
  },
  {
    "aptNm": "시영3차(라이프)아파트",
    "dealAmount": "38,500",
    "date": "2026-03-10",
    "floor": 12,
    "area": 39.6
  },
  {
    "aptNm": "시영3차(라이프)아파트",
    "dealAmount": "31,900",
    "date": "2026-03-09",
    "floor": 5,
    "area": 34.44
  },
  {
    "aptNm": "대구역 서희스타힐스",
    "dealAmount": "31,400",
    "date": "2026-03-08",
    "floor": 15,
    "area": 59.87
  },
  {
    "aptNm": "시영3차(라이프)아파트",
    "dealAmount": "36,800",
    "date": "2026-03-07",
    "floor": 9,
    "area": 39.6
  },
  {
    "aptNm": "대구역 서희스타힐스",
    "dealAmount": "32,900",
    "date": "2026-03-06",
    "floor": 19,
    "area": 59.91
  },
  {
    "aptNm": "대구역 서희스타힐스",
    "dealAmount": "45,000",
    "date": "2026-03-03",
    "floor": 4,
    "area": 115.98
  },
  {
    "aptNm": "시영3차(라이프)아파트",
    "dealAmount": "30,500",
    "date": "2026-03-03",
    "floor": 7,
    "area": 34.44
  },
  {
    "aptNm": "대구역 서희스타힐스",
    "dealAmount": "29,300",
    "date": "2026-02-28",
    "floor": 4,
    "area": 59.87
  },
  {
    "aptNm": "서창베라체아파트(11단지)",
    "dealAmount": "33,000",
    "date": "2026-02-28",
    "floor": 10,
    "area": 59.85
  },
  {
    "aptNm": "대구역 서희스타힐스",
    "dealAmount": "38,750",
    "date": "2026-02-24",
    "floor": 24,
    "area": 84.49
  },
  {
    "aptNm": "시영3차(라이프)아파트",
    "dealAmount": "41,500",
    "date": "2026-02-23",
    "floor": 11,
    "area": 39.6
  },
  {
    "aptNm": "대구역 서희스타힐스",
    "dealAmount": "32,000",
    "date": "2026-02-21",
    "floor": 8,
    "area": 59.91
  },
  {
    "aptNm": "등촌동아이파크",
    "dealAmount": "134,000",
    "date": "2026-02-21",
    "floor": 8,
    "area": 134.8836
  },
  {
    "aptNm": "시영3차(라이프)아파트",
    "dealAmount": "54,500",
    "date": "2026-02-20",
    "floor": 6,
    "area": 49.5
  },
  {
    "aptNm": "시영3차(라이프)아파트",
    "dealAmount": "32,000",
    "date": "2026-02-20",
    "floor": 3,
    "area": 34.44
  },
  {
    "aptNm": "등촌동아이파크",
    "dealAmount": "123,500",
    "date": "2026-02-19",
    "floor": 20,
    "area": 84.9958
  },
  {
    "aptNm": "등촌동아이파크",
    "dealAmount": "127,000",
    "date": "2026-02-19",
    "floor": 2,
    "area": 134.9883
  },
  {
    "aptNm": "시영3차(라이프)아파트",
    "dealAmount": "38,500",
    "date": "2026-02-19",
    "floor": 13,
    "area": 39.6
  },
  {
    "aptNm": "늘푸른동아",
    "dealAmount": "87,000",
    "date": "2026-02-19",
    "floor": 19,
    "area": 84.97
  },
  {
    "aptNm": "대구역 서희스타힐스",
    "dealAmount": "40,500",
    "date": "2026-02-14",
    "floor": 22,
    "area": 84.84
  },
  {
    "aptNm": "늘푸른동아",
    "dealAmount": "92,000",
    "date": "2026-02-13",
    "floor": 19,
    "area": 114.73
  },
  {
    "aptNm": "등촌동아이파크",
    "dealAmount": "135,000",
    "date": "2026-02-11",
    "floor": 16,
    "area": 119.9031
  },
  {
    "aptNm": "등촌동아이파크",
    "dealAmount": "126,000",
    "date": "2026-02-11",
    "floor": 4,
    "area": 84.9958
  },
  {
    "aptNm": "엘에이치피닉스포레",
    "dealAmount": "39,000",
    "date": "2026-02-09",
    "floor": 3,
    "area": 84.99
  },
  {
    "aptNm": "대구역 서희스타힐스",
    "dealAmount": "41,700",
    "date": "2026-02-08",
    "floor": 15,
    "area": 84.49
  },
  {
    "aptNm": "엘에이치피닉스포레",
    "dealAmount": "47,000",
    "date": "2026-02-07",
    "floor": 11,
    "area": 101.63
  },
  {
    "aptNm": "대구역 서희스타힐스",
    "dealAmount": "29,000",
    "date": "2026-02-07",
    "floor": 15,
    "area": 59.85
  },
  {
    "aptNm": "시영3차(라이프)아파트",
    "dealAmount": "32,700",
    "date": "2026-02-07",
    "floor": 8,
    "area": 34.44
  },
  {
    "aptNm": "대구역 서희스타힐스",
    "dealAmount": "36,000",
    "date": "2026-02-05",
    "floor": 3,
    "area": 84.84
  },
  {
    "aptNm": "등촌동아이파크",
    "dealAmount": "120,000",
    "date": "2026-02-04",
    "floor": 19,
    "area": 84.9958
  },
  {
    "aptNm": "등촌동아이파크",
    "dealAmount": "109,000",
    "date": "2026-02-03",
    "floor": 18,
    "area": 84.7556
  },
  {
    "aptNm": "시영3차(라이프)아파트",
    "dealAmount": "54,000",
    "date": "2026-02-02",
    "floor": 10,
    "area": 49.5
  },
  {
    "aptNm": "서창베라체아파트(11단지)",
    "dealAmount": "32,550",
    "date": "2026-02-01",
    "floor": 9,
    "area": 59.52
  }
]