[
  {
    "aptNm": "일신건영휴먼빌",
    "dealAmount": "26,500",
    "date": "2026-07-15",
    "floor": 2,
    "area": 84.9603
  },
  {
    "aptNm": "일신건영휴먼빌",
    "dealAmount": "29,400",
    "date": "2026-06-13",
    "floor": 14,
    "area": 84.9603
  },
  {
    "aptNm": "일신건영휴먼빌",
    "dealAmount": "29,500",
    "date": "2026-06-11",
    "floor": 16,
    "area": 84.9603
  },
  {
    "aptNm": "일신건영휴먼빌",
    "dealAmount": "26,800",
    "date": "2026-06-04",
    "floor": 14,
    "area": 84.9603
  },
  {
    "aptNm": "일신건영휴먼빌",
    "dealAmount": "28,000",
    "date": "2026-05-20",
    "floor": 13,
    "area": 84.9603
  },
  {
    "aptNm": "일신건영휴먼빌",
    "dealAmount": "25,000",
    "date": "2026-05-07",
    "floor": 1,
    "area": 84.9603
  },
  {
    "aptNm": "일신건영휴먼빌",
    "dealAmount": "23,000",
    "date": "2026-04-26",
    "floor": 4,
    "area": 59.9958
  },
  {
    "aptNm": "일신건영휴먼빌",
    "dealAmount": "26,000",
    "date": "2026-04-14",
    "floor": 11,
    "area": 84.9603
  },
  {
    "aptNm": "일신건영휴먼빌",
    "dealAmount": "26,000",
    "date": "2026-03-14",
    "floor": 5,
    "area": 84.9603
  },
  {
    "aptNm": "일신건영휴먼빌",
    "dealAmount": "26,300",
    "date": "2026-03-02",
    "floor": 17,
    "area": 84.9603
  },
  {
    "aptNm": "일신건영휴먼빌",
    "dealAmount": "26,200",
    "date": "2026-02-13",
    "floor": 10,
    "area": 84.9603
  },
  {
    "aptNm": "일신건영휴먼빌",
    "dealAmount": "28,500",
    "date": "2026-02-04",
    "floor": 6,
    "area": 84.9603
  },
  {
    "aptNm": "일신건영휴먼빌",
    "dealAmount": "26,000",
    "date": "2026-02-03",
    "floor": 24,
    "area": 84.9603
  },
  {
    "aptNm": "일신건영휴먼빌",
    "dealAmount": "43,000",
    "date": "2026-02-02",
    "floor": 2,
    "area": 117.7025
  }
]