[
  {
    "aptNm": "원주단구내안애카운티에듀파크2단지",
    "dealAmount": "30,500",
    "date": "2026-07-01",
    "floor": 17,
    "area": 84.9317
  },
  {
    "aptNm": "원주단구내안애카운티에듀파크2단지",
    "dealAmount": "28,400",
    "date": "2026-06-25",
    "floor": 1,
    "area": 84.9024
  },
  {
    "aptNm": "서대구역화성파크드림",
    "dealAmount": "34,000",
    "date": "2026-06-25",
    "floor": 2,
    "area": 59.9785
  },
  {
    "aptNm": "원주단구내안애카운티에듀파크2단지",
    "dealAmount": "31,500",
    "date": "2026-06-22",
    "floor": 16,
    "area": 84.8784
  },
  {
    "aptNm": "서대구역화성파크드림",
    "dealAmount": "35,800",
    "date": "2026-06-18",
    "floor": 21,
    "area": 59.9533
  },
  {
    "aptNm": "책향기마을14단지우남퍼스트빌(1711)",
    "dealAmount": "36,500",
    "date": "2026-06-17",
    "floor": 4,
    "area": 101.9776
  },
  {
    "aptNm": "서대구역화성파크드림",
    "dealAmount": "50,300",
    "date": "2026-06-17",
    "floor": 13,
    "area": 84.9957
  },
  {
    "aptNm": "책향기마을14단지우남퍼스트빌(1711)",
    "dealAmount": "40,000",
    "date": "2026-06-14",
    "floor": 7,
    "area": 101.9776
  },
  {
    "aptNm": "원주단구내안애카운티에듀파크2단지",
    "dealAmount": "31,200",
    "date": "2026-06-11",
    "floor": 14,
    "area": 84.9317
  },
  {
    "aptNm": "책향기마을14단지우남퍼스트빌(1711)",
    "dealAmount": "43,500",
    "date": "2026-06-06",
    "floor": 14,
    "area": 101.9776
  },
  {
    "aptNm": "원주단구내안애카운티에듀파크2단지",
    "dealAmount": "29,500",
    "date": "2026-06-01",
    "floor": 3,
    "area": 84.9025
  },
  {
    "aptNm": "원주단구내안애카운티에듀파크2단지",
    "dealAmount": "32,200",
    "date": "2026-05-28",
    "floor": 16,
    "area": 84.9024
  },
  {
    "aptNm": "서대구역화성파크드림",
    "dealAmount": "36,500",
    "date": "2026-05-27",
    "floor": 23,
    "area": 59.9533
  },
  {
    "aptNm": "서대구역화성파크드림",
    "dealAmount": "44,000",
    "date": "2026-05-25",
    "floor": 24,
    "area": 74.8839
  },
  {
    "aptNm": "서대구역화성파크드림",
    "dealAmount": "41,900",
    "date": "2026-05-21",
    "floor": 4,
    "area": 74.8982
  },
  {
    "aptNm": "원주단구내안애카운티에듀파크2단지",
    "dealAmount": "31,300",
    "date": "2026-05-20",
    "floor": 6,
    "area": 84.9317
  },
  {
    "aptNm": "서대구역화성파크드림",
    "dealAmount": "36,000",
    "date": "2026-05-20",
    "floor": 10,
    "area": 59.9533
  },
  {
    "aptNm": "서대구역화성파크드림",
    "dealAmount": "53,000",
    "date": "2026-05-15",
    "floor": 3,
    "area": 99.4861
  },
  {
    "aptNm": "원주단구내안애카운티에듀파크2단지",
    "dealAmount": "31,700",
    "date": "2026-05-02",
    "floor": 17,
    "area": 84.9024
  },
  {
    "aptNm": "서대구역화성파크드림",
    "dealAmount": "42,800",
    "date": "2026-05-01",
    "floor": 18,
    "area": 74.8839
  },
  {
    "aptNm": "원주단구내안애카운티에듀파크2단지",
    "dealAmount": "30,800",
    "date": "2026-04-24",
    "floor": 5,
    "area": 84.9024
  },
  {
    "aptNm": "책향기마을14단지우남퍼스트빌(1711)",
    "dealAmount": "43,000",
    "date": "2026-04-22",
    "floor": 7,
    "area": 146.7574
  },
  {
    "aptNm": "서대구역화성파크드림",
    "dealAmount": "48,000",
    "date": "2026-04-18",
    "floor": 3,
    "area": 84.929
  },
  {
    "aptNm": "서대구역화성파크드림",
    "dealAmount": "36,000",
    "date": "2026-04-14",
    "floor": 11,
    "area": 59.9533
  },
  {
    "aptNm": "서대구역화성파크드림",
    "dealAmount": "37,700",
    "date": "2026-04-13",
    "floor": 25,
    "area": 59.9533
  },
  {
    "aptNm": "책향기마을14단지우남퍼스트빌(1711)",
    "dealAmount": "37,000",
    "date": "2026-04-10",
    "floor": 3,
    "area": 101.9776
  },
  {
    "aptNm": "원주단구내안애카운티에듀파크2단지",
    "dealAmount": "29,000",
    "date": "2026-04-08",
    "floor": 13,
    "area": 84.9317
  },
  {
    "aptNm": "서대구역화성파크드림",
    "dealAmount": "56,700",
    "date": "2026-04-08",
    "floor": 13,
    "area": 99.4861
  },
  {
    "aptNm": "원주단구내안애카운티에듀파크2단지",
    "dealAmount": "33,500",
    "date": "2026-04-01",
    "floor": 20,
    "area": 84.9317
  },
  {
    "aptNm": "원주단구내안애카운티에듀파크2단지",
    "dealAmount": "31,000",
    "date": "2026-03-28",
    "floor": 19,
    "area": 84.9317
  },
  {
    "aptNm": "서대구역화성파크드림",
    "dealAmount": "49,400",
    "date": "2026-03-28",
    "floor": 28,
    "area": 84.9735
  },
  {
    "aptNm": "서대구역화성파크드림",
    "dealAmount": "46,800",
    "date": "2026-03-25",
    "floor": 8,
    "area": 84.9735
  },
  {
    "aptNm": "서대구역화성파크드림",
    "dealAmount": "35,000",
    "date": "2026-03-23",
    "floor": 15,
    "area": 59.9533
  },
  {
    "aptNm": "서대구역화성파크드림",
    "dealAmount": "41,400",
    "date": "2026-03-21",
    "floor": 5,
    "area": 74.8982
  },
  {
    "aptNm": "서대구역화성파크드림",
    "dealAmount": "47,500",
    "date": "2026-03-19",
    "floor": 11,
    "area": 84.929
  },
  {
    "aptNm": "서대구역화성파크드림",
    "dealAmount": "49,700",
    "date": "2026-03-16",
    "floor": 24,
    "area": 84.929
  },
  {
    "aptNm": "책향기마을14단지우남퍼스트빌(1711)",
    "dealAmount": "40,000",
    "date": "2026-03-09",
    "floor": 2,
    "area": 101.9776
  },
  {
    "aptNm": "서대구역화성파크드림",
    "dealAmount": "46,500",
    "date": "2026-03-07",
    "floor": 16,
    "area": 84.9735
  },
  {
    "aptNm": "서대구역화성파크드림",
    "dealAmount": "56,000",
    "date": "2026-03-04",
    "floor": 22,
    "area": 99.4861
  },
  {
    "aptNm": "서대구역화성파크드림",
    "dealAmount": "46,700",
    "date": "2026-03-03",
    "floor": 28,
    "area": 84.9735
  },
  {
    "aptNm": "서대구역화성파크드림",
    "dealAmount": "47,900",
    "date": "2026-02-24",
    "floor": 23,
    "area": 84.9735
  },
  {
    "aptNm": "서대구역화성파크드림",
    "dealAmount": "46,900",
    "date": "2026-02-23",
    "floor": 15,
    "area": 84.9735
  },
  {
    "aptNm": "서대구역화성파크드림",
    "dealAmount": "48,100",
    "date": "2026-02-19",
    "floor": 22,
    "area": 84.929
  },
  {
    "aptNm": "서대구역화성파크드림",
    "dealAmount": "49,500",
    "date": "2026-02-09",
    "floor": 4,
    "area": 84.929
  },
  {
    "aptNm": "서대구역화성파크드림",
    "dealAmount": "49,000",
    "date": "2026-02-09",
    "floor": 20,
    "area": 84.929
  },
  {
    "aptNm": "서대구역화성파크드림",
    "dealAmount": "41,800",
    "date": "2026-02-08",
    "floor": 15,
    "area": 74.8982
  },
  {
    "aptNm": "서대구역화성파크드림",
    "dealAmount": "35,500",
    "date": "2026-02-07",
    "floor": 9,
    "area": 59.9785
  },
  {
    "aptNm": "서대구역화성파크드림",
    "dealAmount": "37,700",
    "date": "2026-02-06",
    "floor": 9,
    "area": 59.9533
  },
  {
    "aptNm": "원주단구내안애카운티에듀파크2단지",
    "dealAmount": "32,650",
    "date": "2026-02-04",
    "floor": 14,
    "area": 84.9317
  }
]