[
  {
    "aptNm": "광명역파크자이",
    "dealAmount": "108,000",
    "date": "2024-06-30",
    "floor": 12,
    "area": 84.9636
  },
  {
    "aptNm": "광명역파크자이",
    "dealAmount": "107,000",
    "date": "2024-06-08",
    "floor": 7,
    "area": 84.9636
  },
  {
    "aptNm": "광명역파크자이",
    "dealAmount": "109,000",
    "date": "2024-06-08",
    "floor": 26,
    "area": 84.9314
  },
  {
    "aptNm": "광명역파크자이",
    "dealAmount": "113,000",
    "date": "2024-06-08",
    "floor": 7,
    "area": 84.9636
  },
  {
    "aptNm": "광명역파크자이",
    "dealAmount": "110,000",
    "date": "2024-06-01",
    "floor": 35,
    "area": 84.9636
  },
  {
    "aptNm": "광명역파크자이",
    "dealAmount": "90,000",
    "date": "2024-05-31",
    "floor": 6,
    "area": 59.9678
  },
  {
    "aptNm": "광명역파크자이",
    "dealAmount": "110,000",
    "date": "2024-05-30",
    "floor": 16,
    "area": 84.9636
  },
  {
    "aptNm": "광명역파크자이",
    "dealAmount": "107,700",
    "date": "2024-05-21",
    "floor": 36,
    "area": 84.9636
  },
  {
    "aptNm": "광명역파크자이",
    "dealAmount": "106,700",
    "date": "2024-05-18",
    "floor": 17,
    "area": 84.9314
  },
  {
    "aptNm": "광명역파크자이",
    "dealAmount": "91,000",
    "date": "2024-05-01",
    "floor": 21,
    "area": 59.802
  },
  {
    "aptNm": "광명역파크자이",
    "dealAmount": "91,000",
    "date": "2024-05-01",
    "floor": 21,
    "area": 59.802
  },
  {
    "aptNm": "광명역파크자이",
    "dealAmount": "106,000",
    "date": "2024-04-26",
    "floor": 14,
    "area": 84.9314
  },
  {
    "aptNm": "광명역파크자이",
    "dealAmount": "106,000",
    "date": "2024-04-23",
    "floor": 12,
    "area": 84.9314
  },
  {
    "aptNm": "광명역파크자이",
    "dealAmount": "106,000",
    "date": "2024-04-23",
    "floor": 12,
    "area": 84.9314
  },
  {
    "aptNm": "광명역파크자이",
    "dealAmount": "92,000",
    "date": "2024-04-20",
    "floor": 21,
    "area": 59.9678
  },
  {
    "aptNm": "광명역파크자이",
    "dealAmount": "109,500",
    "date": "2024-04-13",
    "floor": 20,
    "area": 84.9636
  },
  {
    "aptNm": "광명역파크자이",
    "dealAmount": "106,000",
    "date": "2024-03-23",
    "floor": 24,
    "area": 84.9314
  },
  {
    "aptNm": "광명역파크자이",
    "dealAmount": "106,000",
    "date": "2024-03-23",
    "floor": 24,
    "area": 84.9314
  },
  {
    "aptNm": "광명역파크자이",
    "dealAmount": "106,000",
    "date": "2024-03-22",
    "floor": 15,
    "area": 84.9314
  },
  {
    "aptNm": "광명역파크자이",
    "dealAmount": "90,000",
    "date": "2024-02-21",
    "floor": 30,
    "area": 59.9678
  },
  {
    "aptNm": "광명역파크자이",
    "dealAmount": "89,000",
    "date": "2024-01-13",
    "floor": 30,
    "area": 59.9678
  }
]